<vector android:height="445.28302dp" android:viewportHeight="590"
    android:viewportWidth="1060" android:width="800dp"
    xmlns:aapt="http://schemas.android.com/aapt" xmlns:android="http://schemas.android.com/apk/res/android">
    <path android:fillColor="#00000000"
        android:pathData="M580,317L499,317C485.8,317 475,306.2 475,293L475,256.5C475,243.3 464.2,232.5 451,232.5L370,232.5"
        android:strokeColor="#757575" android:strokeWidth="4.06"/>
    <path android:fillColor="#00000000"
        android:pathData="M580,317L500.6,317C487.3,317 476.6,327.8 476.6,341L476.6,378.5C476.6,391.7 465.8,402.5 452.6,402.5L370,402.5"
        android:strokeColor="#757575" android:strokeWidth="4.06"/>
    <path android:fillColor="#00000000"
        android:pathData="M1040,125L1040,510C1040,543.1 1013.1,570 980,570L640,570C606.9,570 580,543.1 580,510L580,125C580,91.9 606.9,65 640,65L980,65C1013.1,65 1040,91.9 1040,125Z"
        android:strokeLineCap="butt" android:strokeWidth="3.48">
        <aapt:attr name="android:strokeColor">
            <gradient android:endX="580" android:endY="317.5"
                android:startX="1040" android:startY="317.5" android:type="linear">
                <item android:color="#FFE44857" android:offset="0"/>
                <item android:color="#FFDA4968" android:offset="0.2"/>
                <item android:color="#FFBE4C96" android:offset="0.4"/>
                <item android:color="#FFA74EBC" android:offset="0.6"/>
                <item android:color="#FF9650D9" android:offset="0.7"/>
                <item android:color="#FF8252FB" android:offset="0.9"/>
                <item android:color="#FF7F52FF" android:offset="1"/>
            </gradient>
        </aapt:attr>
    </path>
    <path android:pathData="M1040,125L1040,510C1040,543.1 1013.1,570 980,570L640,570C606.9,570 580,543.1 580,510L580,125C580,91.9 606.9,65 640,65L980,65C1013.1,65 1040,91.9 1040,125Z">
        <aapt:attr name="android:fillColor">
            <gradient android:endX="580" android:endY="317.5"
                android:startX="1040" android:startY="317.5" android:type="linear">
                <item android:color="#33E44857" android:offset="0"/>
                <item android:color="#33DA4968" android:offset="0.2"/>
                <item android:color="#33BE4C96" android:offset="0.4"/>
                <item android:color="#33A74EBC" android:offset="0.6"/>
                <item android:color="#339650D9" android:offset="0.7"/>
                <item android:color="#338252FB" android:offset="0.9"/>
                <item android:color="#337F52FF" android:offset="1"/>
            </gradient>
        </aapt:attr>
    </path>
    <path android:fillColor="#ffffff" android:pathData="M1020,395C1020,419.8 999.8,440 975,440L645,440C620.2,440 600,419.8 600,395C600,370.2 620.2,350 645,350L975,350C999.8,350 1020,370.2 1020,395Z"/>
    <path android:fillColor="#212121" android:fillType="nonZero" android:pathData="M641.3,379.5L650.7,379.5C654,379.5 656.6,380.1 658.3,381.3C660,382.6 660.9,384.4 660.9,386.7C660.9,388.1 660.6,389.3 660,390.3C659.3,391.3 658.3,392.1 657,392.8L657,392.9C658.8,393.6 660,394.5 660.8,395.6C661.6,396.7 662,398.1 662,399.9C662,402.7 661.2,404.8 659.6,406.3C658,407.7 655.6,408.5 652.5,408.5L641.3,408.5L641.3,379.5ZM651.2,391C652.4,391 653.3,390.7 653.9,390.1C654.6,389.4 654.9,388.5 654.9,387.4C654.9,386.2 654.6,385.4 653.8,384.9C653.1,384.3 652,384.1 650.5,384.1L647.3,384.1L647.3,391L651.2,391ZM652.1,403.9C653.4,403.9 654.4,403.5 655.1,402.7C655.8,402 656.1,400.9 656.1,399.6C656.1,398.1 655.7,397 654.8,396.4C654,395.7 652.6,395.4 650.7,395.4L647.3,395.4L647.3,403.9L652.1,403.9Z"/>
    <path android:fillColor="#212121" android:fillType="nonZero" android:pathData="M672.8,408.9C670.4,408.9 668.6,408.1 667.4,406.5C666.2,404.9 665.6,402.5 665.6,399.4L665.6,387.8L670.8,387.8L670.8,399.5C670.8,401.2 671.1,402.5 671.7,403.4C672.3,404.2 673.2,404.6 674.4,404.6C675.9,404.6 677.1,404 678,402.9C678.9,401.8 679.4,400.4 679.4,398.8L679.4,387.8L684.7,387.8L684.7,403.2C684.7,404.6 684.8,406.4 685,408.5L680,408.5C679.8,407.2 679.7,406 679.7,404.8L679.6,404.8C679.1,406.1 678.2,407 677,407.8C675.8,408.5 674.4,408.9 672.8,408.9Z"/>
    <path android:fillColor="#212121" android:fillType="nonZero" android:pathData="M695.5,408.9C693.7,408.9 692.1,408.5 690.8,407.8C689.4,407.1 688.4,406.1 687.9,404.9L691.2,402.7C691.7,403.4 692.3,403.9 693.1,404.3C693.8,404.7 694.6,404.9 695.4,404.9C696.4,404.9 697.1,404.7 697.7,404.2C698.3,403.7 698.6,403.1 698.6,402.4C698.6,401.8 698.4,401.4 698,401C697.5,400.7 696.6,400.2 695.2,399.7C692.7,398.7 690.9,397.7 689.9,396.7C688.9,395.8 688.3,394.5 688.3,393.1C688.3,391.4 689,390 690.4,388.9C691.8,387.9 693.7,387.4 696,387.4C697.5,387.4 698.9,387.7 700.2,388.2C701.4,388.8 702.4,389.7 703.2,390.8L700.1,393.1C699.2,391.9 697.9,391.3 696.2,391.3C695.4,391.3 694.7,391.4 694.3,391.7C693.8,392 693.6,392.4 693.6,393C693.6,393.4 693.7,393.7 693.9,393.9C694.1,394.2 694.5,394.4 695,394.7C695.6,395 696.4,395.4 697.7,395.8C699.3,396.5 700.5,397.1 701.4,397.7C702.3,398.3 703,398.9 703.3,399.6C703.7,400.3 703.9,401.2 703.9,402.2C703.9,403.5 703.6,404.7 702.8,405.7C702.1,406.7 701.2,407.5 699.9,408C698.6,408.6 697.2,408.9 695.5,408.9Z"/>
    <path android:fillColor="#212121" android:fillType="nonZero" android:pathData="M710.6,385.4C709.6,385.4 708.8,385.1 708.2,384.5C707.6,384 707.3,383.2 707.3,382.3C707.3,381.3 707.6,380.6 708.2,380C708.8,379.4 709.6,379.2 710.6,379.2C711.7,379.2 712.5,379.4 713.1,380C713.7,380.6 714,381.3 714,382.3C714,383.2 713.7,384 713.1,384.5C712.5,385.1 711.7,385.4 710.6,385.4ZM708,387.8L713.3,387.8L713.3,408.5L708,408.5L708,387.8Z"/>
    <path android:fillColor="#212121" android:fillType="nonZero" android:pathData="M718.3,393.2C718.3,390.7 718.2,388.9 718.1,387.8L723.1,387.8C723.2,388.9 723.3,390.1 723.3,391.4L723.4,391.4C723.9,390.2 724.8,389.2 726,388.5C727.3,387.7 728.7,387.4 730.2,387.4C732.6,387.4 734.4,388.2 735.6,389.8C736.8,391.4 737.4,393.7 737.4,396.8L737.4,408.5L732.2,408.5L732.2,396.8C732.2,395 731.9,393.7 731.3,392.9C730.7,392 729.8,391.6 728.5,391.6C727.1,391.6 725.9,392.1 724.9,393.2C724,394.2 723.6,395.5 723.6,397.2L723.6,408.5L718.3,408.5L718.3,393.2Z"/>
    <path android:fillColor="#212121" android:fillType="nonZero" android:pathData="M760.7,400.1L746.3,400.1C746.8,403 748.5,404.4 751.4,404.4C752.7,404.4 753.7,404.2 754.6,403.8C755.5,403.4 756.4,402.7 757.2,401.8L760.1,404.5C759.3,405.8 758.1,406.9 756.5,407.7C754.9,408.5 753.1,408.9 751.1,408.9C747.9,408.9 745.4,407.9 743.6,406C741.8,404.1 740.9,401.5 740.9,398.2C740.9,394.8 741.8,392.2 743.6,390.3C745.4,388.3 747.9,387.4 751.1,387.4C754.1,387.4 756.5,388.3 758.2,390.2C759.9,392.1 760.7,394.8 760.7,398.2L760.7,400.1ZM755.6,396.2C755.6,394.8 755.2,393.7 754.4,392.9C753.5,392.1 752.4,391.7 751,391.7C749.7,391.7 748.6,392.1 747.8,392.9C747,393.8 746.5,394.9 746.3,396.5L755.6,396.5L755.6,396.2Z"/>
    <path android:fillColor="#212121" android:fillType="nonZero" android:pathData="M771.6,408.9C769.8,408.9 768.2,408.5 766.8,407.8C765.5,407.1 764.5,406.1 764,404.9L767.2,402.7C767.7,403.4 768.4,403.9 769.1,404.3C769.9,404.7 770.7,404.9 771.5,404.9C772.4,404.9 773.2,404.7 773.8,404.2C774.4,403.7 774.7,403.1 774.7,402.4C774.7,401.8 774.5,401.4 774.1,401C773.6,400.7 772.7,400.2 771.3,399.7C768.7,398.7 767,397.7 766,396.7C764.9,395.8 764.4,394.5 764.4,393.1C764.4,391.4 765.1,390 766.5,388.9C767.9,387.9 769.8,387.4 772.1,387.4C773.6,387.4 775,387.7 776.3,388.2C777.5,388.8 778.5,389.7 779.3,390.8L776.2,393.1C775.3,391.9 773.9,391.3 772.3,391.3C771.5,391.3 770.8,391.4 770.4,391.7C769.9,392 769.7,392.4 769.7,393C769.7,393.4 769.8,393.7 770,393.9C770.2,394.2 770.5,394.4 771.1,394.7C771.6,395 772.5,395.4 773.7,395.8C775.4,396.5 776.6,397.1 777.5,397.7C778.4,398.3 779.1,398.9 779.4,399.6C779.8,400.3 780,401.2 780,402.2C780,403.5 779.6,404.7 778.9,405.7C778.2,406.7 777.2,407.5 776,408C774.7,408.6 773.2,408.9 771.6,408.9Z"/>
    <path android:fillColor="#212121" android:fillType="nonZero" android:pathData="M789.8,408.9C788,408.9 786.5,408.5 785.1,407.8C783.7,407.1 782.8,406.1 782.2,404.9L785.5,402.7C786,403.4 786.6,403.9 787.4,404.3C788.2,404.7 788.9,404.9 789.7,404.9C790.7,404.9 791.5,404.7 792.1,404.2C792.7,403.7 793,403.1 793,402.4C793,401.8 792.8,401.4 792.3,401C791.9,400.7 790.9,400.2 789.5,399.7C787,398.7 785.2,397.7 784.2,396.7C783.2,395.8 782.7,394.5 782.7,393.1C782.7,391.4 783.4,390 784.8,388.9C786.2,387.9 788,387.4 790.3,387.4C791.9,387.4 793.3,387.7 794.5,388.2C795.7,388.8 796.8,389.7 797.5,390.8L794.5,393.1C793.5,391.9 792.2,391.3 790.5,391.3C789.7,391.3 789.1,391.4 788.6,391.7C788.2,392 787.9,392.4 787.9,393C787.9,393.4 788,393.7 788.2,393.9C788.4,394.2 788.8,394.4 789.3,394.7C789.9,395 790.8,395.4 792,395.8C793.6,396.5 794.9,397.1 795.8,397.7C796.7,398.3 797.3,398.9 797.7,399.6C798,400.3 798.2,401.2 798.2,402.2C798.2,403.5 797.9,404.7 797.2,405.7C796.5,406.7 795.5,407.5 794.2,408C792.9,408.6 791.5,408.9 789.8,408.9Z"/>
    <path android:fillColor="#212121" android:fillType="nonZero" android:pathData="M823.8,378.5L829.2,378.5L813.5,410.2L808.1,410.2L823.8,378.5Z"/>
    <path android:fillColor="#212121" android:fillType="nonZero" android:pathData="M840.8,379.5L851.1,379.5C859.1,379.5 863,384.1 863,393.4C863,397 862.6,399.9 861.7,402.1C860.8,404.3 859.4,405.9 857.5,406.9C855.6,407.9 853.1,408.5 850,408.5L840.8,408.5L840.8,379.5ZM850.6,403.7C852.2,403.7 853.5,403.4 854.4,402.7C855.3,402 856,400.9 856.5,399.4C856.9,397.9 857.1,395.9 857.1,393.4C857.1,390.2 856.6,387.8 855.7,386.4C854.8,385 853.2,384.3 851,384.3L846.8,384.3L846.8,403.7L850.6,403.7Z"/>
    <path android:fillColor="#212121" android:fillType="nonZero" android:pathData="M876.5,408.9C873.2,408.9 870.6,407.9 868.7,406C866.8,404.1 865.9,401.5 865.9,398.1C865.9,394.7 866.8,392.1 868.7,390.2C870.6,388.3 873.2,387.4 876.5,387.4C879.8,387.4 882.5,388.3 884.3,390.2C886.2,392.1 887.2,394.7 887.2,398.1C887.2,401.5 886.2,404.1 884.3,406C882.5,407.9 879.8,408.9 876.5,408.9ZM876.5,404.9C878.2,404.9 879.5,404.3 880.5,403.1C881.4,401.9 881.9,400.2 881.9,398.1C881.9,396 881.4,394.3 880.5,393.1C879.5,391.9 878.2,391.3 876.5,391.3C874.8,391.3 873.5,391.9 872.6,393.1C871.6,394.3 871.1,396 871.1,398.1C871.1,400.2 871.6,401.9 872.6,403.1C873.5,404.3 874.8,404.9 876.5,404.9Z"/>
    <path android:fillColor="#212121" android:fillType="nonZero" android:pathData="M890.5,393.3C890.5,390.5 890.4,388.7 890.3,387.8L895,387.8C895.1,388.9 895.2,390.1 895.2,391.4L895.2,391.4C895.7,390.1 896.5,389.1 897.6,388.4C898.8,387.7 900.2,387.4 901.7,387.4C903.2,387.4 904.5,387.7 905.5,388.3C906.6,389 907.3,389.9 907.6,391C908.2,389.9 909,389 910.1,388.3C911.3,387.7 912.5,387.4 913.9,387.4C916.2,387.4 918,388.1 919.3,389.6C920.7,391 921.3,393.1 921.3,395.7L921.3,408.5L916.1,408.5L916.1,396.3C916.1,394.8 915.7,393.7 915.1,392.8C914.5,392 913.6,391.6 912.5,391.6C911.3,391.6 910.3,392 909.6,392.9C908.8,393.7 908.5,394.9 908.5,396.3L908.5,408.5L903.3,408.5L903.3,396.4C903.3,394.9 903,393.7 902.4,392.9C901.8,392 900.9,391.6 899.8,391.6C898.6,391.6 897.6,392.1 896.9,393C896.1,393.9 895.7,395 895.7,396.4L895.7,408.5L890.5,408.5L890.5,393.3Z"/>
    <path android:fillColor="#212121" android:fillType="nonZero" android:pathData="M931.8,408.9C930.5,408.9 929.3,408.6 928.2,408C927.1,407.5 926.3,406.7 925.7,405.7C925,404.7 924.7,403.5 924.7,402.3C924.7,400.2 925.6,398.5 927.3,397.4C928.9,396.3 931.3,395.7 934.5,395.7L937.7,395.7L937.7,394.8C937.7,393.7 937.4,392.9 936.7,392.3C936.1,391.7 935.2,391.4 934,391.4C932.7,391.4 931.5,391.6 930.4,392.1C929.3,392.5 928.4,393.1 927.6,393.9L925.3,390.8C926.5,389.8 927.8,388.9 929.3,388.3C930.9,387.7 932.5,387.4 934.1,387.4C936.9,387.4 939.1,388 940.6,389.3C942.2,390.6 943,392.4 943,394.7L943,404.1C943,404.7 943,405.5 943.1,406.3C943.2,407.2 943.3,407.9 943.5,408.5L938.8,408.5C938.6,408.1 938.5,407.7 938.4,407.4C938.4,407.1 938.3,406.6 938.2,406L938.1,406C936.6,407.9 934.5,408.9 931.8,408.9ZM933.1,404.9C934.4,404.9 935.5,404.6 936.4,403.9C937.3,403.2 937.7,402.3 937.7,401.3L937.7,399.2L934.3,399.2C932.9,399.2 931.8,399.5 931.1,400C930.3,400.5 929.9,401.3 929.9,402.3C929.9,403.1 930.2,403.8 930.8,404.2C931.3,404.7 932.1,404.9 933.1,404.9Z"/>
    <path android:fillColor="#212121" android:fillType="nonZero" android:pathData="M951,385.4C950,385.4 949.2,385.1 948.6,384.5C948,384 947.7,383.2 947.7,382.3C947.7,381.3 948,380.6 948.6,380C949.2,379.4 950,379.2 951,379.2C952,379.2 952.9,379.4 953.5,380C954.1,380.6 954.4,381.3 954.4,382.3C954.4,383.2 954.1,384 953.5,384.5C952.9,385.1 952.1,385.4 951,385.4ZM948.4,387.8L953.7,387.8L953.7,408.5L948.4,408.5L948.4,387.8Z"/>
    <path android:fillColor="#212121" android:fillType="nonZero" android:pathData="M958.6,393.2C958.6,390.7 958.6,388.9 958.5,387.8L963.4,387.8C963.6,388.9 963.6,390.1 963.6,391.4L963.8,391.4C964.3,390.2 965.1,389.2 966.4,388.5C967.6,387.7 969,387.4 970.6,387.4C973,387.4 974.7,388.2 976,389.8C977.2,391.4 977.8,393.7 977.8,396.8L977.8,408.5L972.5,408.5L972.5,396.8C972.5,395 972.2,393.7 971.7,392.9C971.1,392 970.2,391.6 968.9,391.6C967.4,391.6 966.2,392.1 965.3,393.2C964.4,394.2 963.9,395.5 963.9,397.2L963.9,408.5L958.6,408.5L958.6,393.2Z"/>
    <path android:fillColor="#ffffff" android:pathData="M1020,505C1020,529.8 999.8,550 975,550L645,550C620.2,550 600,529.8 600,505C600,480.2 620.2,460 645,460L975,460C999.8,460 1020,480.2 1020,505Z"/>
    <path android:fillColor="#212121" android:fillType="nonZero" android:pathData="M705.1,489.5L715.4,489.5C723.4,489.5 727.3,494.1 727.3,503.4C727.3,507 726.9,509.9 726,512.1C725.1,514.3 723.7,515.9 721.8,516.9C719.9,517.9 717.4,518.5 714.3,518.5L705.1,518.5L705.1,489.5ZM714.9,513.7C716.5,513.7 717.8,513.4 718.7,512.7C719.6,512 720.3,510.9 720.8,509.4C721.2,507.9 721.4,505.9 721.4,503.4C721.4,500.2 720.9,497.8 720,496.4C719.1,495 717.5,494.3 715.3,494.3L711.1,494.3L711.1,513.7L714.9,513.7Z"/>
    <path android:fillColor="#212121" android:fillType="nonZero" android:pathData="M737.2,518.9C735.8,518.9 734.6,518.6 733.5,518C732.4,517.5 731.6,516.7 731,515.7C730.4,514.7 730.1,513.5 730.1,512.3C730.1,510.2 730.9,508.5 732.6,507.4C734.3,506.3 736.7,505.7 739.8,505.7L743,505.7L743,504.8C743,503.7 742.7,502.9 742.1,502.3C741.4,501.7 740.5,501.4 739.3,501.4C738.1,501.4 736.9,501.6 735.8,502.1C734.6,502.5 733.7,503.1 733,503.9L730.7,500.8C731.8,499.8 733.1,498.9 734.7,498.3C736.2,497.7 737.8,497.4 739.5,497.4C742.2,497.4 744.4,498 746,499.3C747.5,500.6 748.3,502.4 748.3,504.7L748.3,514.1C748.3,514.7 748.4,515.5 748.5,516.3C748.6,517.2 748.7,517.9 748.8,518.5L744.2,518.5C744,518.1 743.9,517.7 743.8,517.4C743.7,517.1 743.6,516.6 743.6,516L743.5,516C741.9,517.9 739.8,518.9 737.2,518.9ZM738.4,514.9C739.8,514.9 740.9,514.6 741.7,513.9C742.6,513.2 743,512.3 743,511.3L743,509.2L739.6,509.2C738.2,509.2 737.2,509.5 736.4,510C735.6,510.5 735.3,511.3 735.3,512.3C735.3,513.1 735.5,513.8 736.1,514.2C736.7,514.7 737.4,514.9 738.4,514.9Z"/>
    <path android:fillColor="#212121" android:fillType="nonZero" android:pathData="M761.7,518.9C759.6,518.9 758,518.3 756.8,517.1C755.6,516 755,514.3 755,512.2L755,501.7L751.2,501.7L751.2,497.8L755,497.8L755,492.4L760.1,490.9L760.3,490.9L760.3,497.8L766.3,497.8L766.3,501.7L760.3,501.7L760.3,511.5C760.3,512.6 760.6,513.5 761.1,514.1C761.7,514.6 762.5,514.9 763.6,514.9C764.7,514.9 765.7,514.7 766.7,514.4L766.9,518C765.7,518.6 763.9,518.9 761.7,518.9Z"/>
    <path android:fillColor="#212121" android:fillType="nonZero" android:pathData="M776.4,518.9C775.1,518.9 773.9,518.6 772.8,518C771.7,517.5 770.9,516.7 770.3,515.7C769.6,514.7 769.3,513.5 769.3,512.3C769.3,510.2 770.2,508.5 771.9,507.4C773.6,506.3 776,505.7 779.1,505.7L782.3,505.7L782.3,504.8C782.3,503.7 782,502.9 781.3,502.3C780.7,501.7 779.8,501.4 778.6,501.4C777.3,501.4 776.1,501.6 775,502.1C773.9,502.5 773,503.1 772.2,503.9L769.9,500.8C771.1,499.8 772.4,498.9 773.9,498.3C775.5,497.7 777.1,497.4 778.7,497.4C781.5,497.4 783.7,498 785.2,499.3C786.8,500.6 787.6,502.4 787.6,504.7L787.6,514.1C787.6,514.7 787.6,515.5 787.7,516.3C787.8,517.2 787.9,517.9 788.1,518.5L783.4,518.5C783.2,518.1 783.1,517.7 783,517.4C783,517.1 782.9,516.6 782.8,516L782.8,516C781.2,517.9 779.1,518.9 776.4,518.9ZM777.7,514.9C779,514.9 780.1,514.6 781,513.9C781.9,513.2 782.3,512.3 782.3,511.3L782.3,509.2L778.9,509.2C777.5,509.2 776.4,509.5 775.7,510C774.9,510.5 774.5,511.3 774.5,512.3C774.5,513.1 774.8,513.8 775.4,514.2C775.9,514.7 776.7,514.9 777.7,514.9Z"/>
    <path android:fillColor="#212121" android:fillType="nonZero" android:pathData="M814.5,488.5L819.9,488.5L804.1,520.2L798.8,520.2L814.5,488.5Z"/>
    <path android:fillColor="#212121" android:fillType="nonZero" android:pathData="M843.3,518.9C840.6,518.9 838.3,518.3 836.2,517C834.2,515.8 832.6,514.1 831.5,511.9C830.5,509.6 829.9,507 829.9,504C829.9,501 830.5,498.3 831.5,496.1C832.6,493.8 834.2,492.1 836.2,490.9C838.3,489.7 840.6,489.1 843.4,489.1C845.7,489.1 847.7,489.5 849.4,490.4C851.1,491.3 852.4,492.5 853.2,494.2L849.9,497.1C848.4,494.9 846.3,493.8 843.4,493.8C841,493.8 839.1,494.7 837.8,496.4C836.5,498.1 835.9,500.7 835.9,504C835.9,507.3 836.5,509.8 837.8,511.5C839,513.2 840.9,514.1 843.3,514.1C846.3,514.1 848.4,513 849.9,510.8L853.2,513.8C852.4,515.4 851.1,516.7 849.4,517.5C847.7,518.4 845.7,518.9 843.3,518.9Z"/>
    <path android:fillColor="#212121" android:fillType="nonZero" android:pathData="M866.2,518.9C862.9,518.9 860.3,517.9 858.4,516C856.5,514.1 855.6,511.5 855.6,508.1C855.6,504.7 856.5,502.1 858.4,500.2C860.3,498.3 862.9,497.4 866.2,497.4C869.6,497.4 872.2,498.3 874.1,500.2C876,502.1 876.9,504.7 876.9,508.1C876.9,511.5 876,514.1 874.1,516C872.2,517.9 869.6,518.9 866.2,518.9ZM866.2,514.9C867.9,514.9 869.2,514.3 870.2,513.1C871.2,511.9 871.7,510.2 871.7,508.1C871.7,506 871.2,504.3 870.2,503.1C869.2,501.9 867.9,501.3 866.2,501.3C864.6,501.3 863.2,501.9 862.3,503.1C861.3,504.3 860.9,506 860.9,508.1C860.9,510.2 861.3,511.9 862.3,513.1C863.2,514.3 864.6,514.9 866.2,514.9Z"/>
    <path android:fillColor="#212121" android:fillType="nonZero" android:pathData="M880.5,502.8C880.5,500.5 880.4,498.8 880.3,497.8L885.4,497.8C885.5,498.8 885.5,500.1 885.5,501.4L885.5,501.8L885.7,501.8C886.2,500.5 887.1,499.4 888.5,498.6C889.8,497.8 891.3,497.4 893,497.4C893.3,497.4 893.7,497.4 894.2,497.5L894.2,501.7C894.1,501.6 893.8,501.6 893.3,501.6C891.9,501.6 890.7,501.9 889.6,502.7C888.4,503.4 887.5,504.3 886.8,505.5C886.1,506.7 885.8,508 885.8,509.4L885.8,518.5L880.5,518.5L880.5,502.8Z"/>
    <path android:fillColor="#212121" android:fillType="nonZero" android:pathData="M915.8,510.1L901.4,510.1C901.8,513 903.5,514.4 906.5,514.4C907.7,514.4 908.8,514.2 909.7,513.8C910.6,513.4 911.4,512.7 912.3,511.8L915.1,514.5C914.3,515.8 913.1,516.9 911.5,517.7C909.9,518.5 908.1,518.9 906.2,518.9C903,518.9 900.5,517.9 898.7,516C896.9,514.1 896,511.5 896,508.2C896,504.8 896.9,502.2 898.7,500.3C900.5,498.3 903,497.4 906.2,497.4C909.2,497.4 911.6,498.3 913.3,500.2C915,502.1 915.8,504.8 915.8,508.2L915.8,510.1ZM910.6,506.2C910.6,504.8 910.2,503.7 909.4,502.9C908.6,502.1 907.5,501.7 906,501.7C904.7,501.7 903.7,502.1 902.9,502.9C902.1,503.8 901.6,504.9 901.4,506.5L910.6,506.5L910.6,506.2Z"/>
    <path android:fillColor="#ffffff" android:pathData="M1020,285C1020,309.8 999.8,330 975,330L645,330C620.2,330 600,309.8 600,285C600,260.2 620.2,240 645,240L975,240C999.8,240 1020,260.2 1020,285Z"/>
    <path android:fillColor="#212121" android:fillType="nonZero" android:pathData="M690.5,269.5L700.1,269.5C703.5,269.5 706.1,270.3 707.9,271.8C709.7,273.4 710.5,275.7 710.5,278.7C710.5,281.9 709.6,284.4 707.8,286C706,287.7 703.4,288.5 699.9,288.5L696.4,288.5L696.4,298.5L690.5,298.5L690.5,269.5ZM700.4,283.8C701.8,283.8 702.9,283.4 703.7,282.5C704.4,281.7 704.8,280.5 704.8,278.9C704.8,277.4 704.4,276.2 703.6,275.4C702.8,274.6 701.6,274.3 700.1,274.3L696.4,274.3L696.4,283.8L700.4,283.8Z"/>
    <path android:fillColor="#212121" android:fillType="nonZero" android:pathData="M714.3,282.8C714.3,280.5 714.3,278.8 714.2,277.8L719.2,277.8C719.3,278.8 719.4,280.1 719.4,281.4L719.4,281.8L719.5,281.8C720,280.5 721,279.4 722.3,278.6C723.6,277.8 725.1,277.4 726.8,277.4C727.2,277.4 727.6,277.4 728.1,277.5L728.1,281.7C728,281.6 727.6,281.6 727.1,281.6C725.8,281.6 724.5,281.9 723.4,282.7C722.2,283.4 721.3,284.3 720.6,285.5C719.9,286.7 719.6,288 719.6,289.4L719.6,298.5L714.3,298.5L714.3,282.8Z"/>
    <path android:fillColor="#212121" android:fillType="nonZero" android:pathData="M749.6,290.1L735.2,290.1C735.7,293 737.4,294.4 740.3,294.4C741.5,294.4 742.6,294.2 743.5,293.8C744.4,293.4 745.3,292.7 746.1,291.8L749,294.5C748.2,295.8 747,296.9 745.4,297.7C743.7,298.5 742,298.9 740,298.9C736.8,298.9 734.3,297.9 732.5,296C730.7,294.1 729.8,291.5 729.8,288.2C729.8,284.8 730.7,282.2 732.5,280.3C734.3,278.3 736.8,277.4 740,277.4C743,277.4 745.4,278.3 747.1,280.2C748.8,282.1 749.6,284.8 749.6,288.2L749.6,290.1ZM744.5,286.2C744.5,284.8 744.1,283.7 743.2,282.9C742.4,282.1 741.3,281.7 739.9,281.7C738.6,281.7 737.5,282.1 736.7,282.9C735.9,283.8 735.4,284.9 735.2,286.5L744.5,286.5L744.5,286.2Z"/>
    <path android:fillColor="#212121" android:fillType="nonZero" android:pathData="M760.5,298.9C758.7,298.9 757.1,298.5 755.7,297.8C754.4,297.1 753.4,296.1 752.9,294.9L756.1,292.7C756.6,293.4 757.3,293.9 758,294.3C758.8,294.7 759.6,294.9 760.4,294.9C761.3,294.9 762.1,294.7 762.7,294.2C763.3,293.7 763.6,293.1 763.6,292.4C763.6,291.8 763.4,291.4 763,291C762.5,290.7 761.6,290.2 760.1,289.7C757.6,288.7 755.9,287.7 754.9,286.7C753.8,285.8 753.3,284.5 753.3,283.1C753.3,281.4 754,280 755.4,278.9C756.8,277.9 758.7,277.4 761,277.4C762.5,277.4 763.9,277.7 765.2,278.2C766.4,278.8 767.4,279.7 768.2,280.8L765.1,283.1C764.1,281.9 762.8,281.3 761.2,281.3C760.4,281.3 759.7,281.4 759.3,281.7C758.8,282 758.6,282.4 758.6,283C758.6,283.4 758.7,283.7 758.9,283.9C759.1,284.2 759.4,284.4 760,284.7C760.5,285 761.4,285.4 762.6,285.8C764.3,286.5 765.5,287.1 766.4,287.7C767.3,288.3 767.9,288.9 768.3,289.6C768.7,290.3 768.9,291.2 768.9,292.2C768.9,293.5 768.5,294.7 767.8,295.7C767.1,296.7 766.1,297.5 764.9,298C763.6,298.6 762.1,298.9 760.5,298.9Z"/>
    <path android:fillColor="#212121" android:fillType="nonZero" android:pathData="M792,290.1L777.6,290.1C778,293 779.7,294.4 782.7,294.4C783.9,294.4 784.9,294.2 785.8,293.8C786.7,293.4 787.6,292.7 788.4,291.8L791.3,294.5C790.5,295.8 789.3,296.9 787.7,297.7C786.1,298.5 784.3,298.9 782.4,298.9C779.1,298.9 776.6,297.9 774.8,296C773,294.1 772.1,291.5 772.1,288.2C772.1,284.8 773,282.2 774.9,280.3C776.7,278.3 779.1,277.4 782.3,277.4C785.4,277.4 787.7,278.3 789.4,280.2C791.1,282.1 792,284.8 792,288.2L792,290.1ZM786.8,286.2C786.8,284.8 786.4,283.7 785.6,282.9C784.8,282.1 783.6,281.7 782.2,281.7C780.9,281.7 779.9,282.1 779.1,282.9C778.3,283.8 777.7,284.9 777.5,286.5L786.8,286.5L786.8,286.2Z"/>
    <path android:fillColor="#212121" android:fillType="nonZero" android:pathData="M795.2,283.2C795.2,280.7 795.1,278.9 795,277.8L800,277.8C800.1,278.9 800.2,280.1 800.2,281.4L800.3,281.4C800.8,280.2 801.7,279.2 802.9,278.5C804.2,277.7 805.6,277.4 807.1,277.4C809.5,277.4 811.3,278.2 812.5,279.8C813.7,281.4 814.3,283.7 814.3,286.8L814.3,298.5L809.1,298.5L809.1,286.8C809.1,285 808.8,283.7 808.2,282.9C807.6,282 806.7,281.6 805.4,281.6C804,281.6 802.8,282.1 801.9,283.2C800.9,284.2 800.5,285.5 800.5,287.2L800.5,298.5L795.2,298.5L795.2,283.2Z"/>
    <path android:fillColor="#212121" android:fillType="nonZero" android:pathData="M827.5,298.9C825.4,298.9 823.8,298.3 822.6,297.1C821.4,296 820.8,294.3 820.8,292.2L820.8,281.7L817,281.7L817,277.8L820.8,277.8L820.8,272.4L825.9,270.9L826.1,270.9L826.1,277.8L832.1,277.8L832.1,281.7L826.1,281.7L826.1,291.5C826.1,292.6 826.4,293.5 826.9,294.1C827.5,294.6 828.3,294.9 829.4,294.9C830.5,294.9 831.5,294.7 832.5,294.4L832.7,298C831.5,298.6 829.7,298.9 827.5,298.9Z"/>
    <path android:fillColor="#212121" android:fillType="nonZero" android:pathData="M842.2,298.9C840.9,298.9 839.7,298.6 838.6,298C837.5,297.5 836.7,296.7 836.1,295.7C835.5,294.7 835.2,293.5 835.2,292.3C835.2,290.2 836,288.5 837.7,287.4C839.4,286.3 841.8,285.7 844.9,285.7L848.1,285.7L848.1,284.8C848.1,283.7 847.8,282.9 847.1,282.3C846.5,281.7 845.6,281.4 844.4,281.4C843.1,281.4 842,281.6 840.8,282.1C839.7,282.5 838.8,283.1 838,283.9L835.7,280.8C836.9,279.8 838.2,278.9 839.7,278.3C841.3,277.7 842.9,277.4 844.5,277.4C847.3,277.4 849.5,278 851,279.3C852.6,280.6 853.4,282.4 853.4,284.7L853.4,294.1C853.4,294.7 853.4,295.5 853.5,296.3C853.6,297.2 853.8,297.9 853.9,298.5L849.2,298.5C849.1,298.1 848.9,297.7 848.8,297.4C848.8,297.1 848.7,296.6 848.6,296L848.6,296C847,297.9 844.9,298.9 842.2,298.9ZM843.5,294.9C844.8,294.9 845.9,294.6 846.8,293.9C847.7,293.2 848.1,292.3 848.1,291.3L848.1,289.2L844.7,289.2C843.3,289.2 842.2,289.5 841.5,290C840.7,290.5 840.3,291.3 840.3,292.3C840.3,293.1 840.6,293.8 841.2,294.2C841.7,294.7 842.5,294.9 843.5,294.9Z"/>
    <path android:fillColor="#212121" android:fillType="nonZero" android:pathData="M866.8,298.9C864.7,298.9 863,298.3 861.8,297.1C860.7,296 860.1,294.3 860.1,292.2L860.1,281.7L856.3,281.7L856.3,277.8L860.1,277.8L860.1,272.4L865.2,270.9L865.4,270.9L865.4,277.8L871.4,277.8L871.4,281.7L865.4,281.7L865.4,291.5C865.4,292.6 865.6,293.5 866.2,294.1C866.7,294.6 867.6,294.9 868.7,294.9C869.8,294.9 870.8,294.7 871.7,294.4L872,298C870.7,298.6 869,298.9 866.8,298.9Z"/>
    <path android:fillColor="#212121" android:fillType="nonZero" android:pathData="M878.8,275.4C877.8,275.4 877,275.1 876.4,274.5C875.8,274 875.4,273.2 875.4,272.3C875.4,271.3 875.8,270.6 876.4,270C877,269.4 877.8,269.2 878.8,269.2C879.8,269.2 880.6,269.4 881.3,270C881.9,270.6 882.2,271.3 882.2,272.3C882.2,273.2 881.9,274 881.3,274.5C880.7,275.1 879.8,275.4 878.8,275.4ZM876.2,277.8L881.4,277.8L881.4,298.5L876.2,298.5L876.2,277.8Z"/>
    <path android:fillColor="#212121" android:fillType="nonZero" android:pathData="M896.4,298.9C893.1,298.9 890.5,297.9 888.6,296C886.7,294.1 885.8,291.5 885.8,288.1C885.8,284.7 886.7,282.1 888.6,280.2C890.5,278.3 893.1,277.4 896.4,277.4C899.8,277.4 902.4,278.3 904.3,280.2C906.2,282.1 907.1,284.7 907.1,288.1C907.1,291.5 906.2,294.1 904.3,296C902.4,297.9 899.8,298.9 896.4,298.9ZM896.4,294.9C898.1,294.9 899.4,294.3 900.4,293.1C901.4,291.9 901.8,290.2 901.8,288.1C901.8,286 901.4,284.3 900.4,283.1C899.4,281.9 898.1,281.3 896.4,281.3C894.7,281.3 893.4,281.9 892.5,283.1C891.5,284.3 891,286 891,288.1C891,290.2 891.5,291.9 892.5,293.1C893.4,294.3 894.7,294.9 896.4,294.9Z"/>
    <path android:fillColor="#212121" android:fillType="nonZero" android:pathData="M910.4,283.2C910.4,280.7 910.3,278.9 910.2,277.8L915.2,277.8C915.3,278.9 915.4,280.1 915.4,281.4L915.5,281.4C916,280.2 916.9,279.2 918.1,278.5C919.4,277.7 920.8,277.4 922.3,277.4C924.7,277.4 926.5,278.2 927.7,279.8C928.9,281.4 929.5,283.7 929.5,286.8L929.5,298.5L924.3,298.5L924.3,286.8C924.3,285 924,283.7 923.4,282.9C922.8,282 921.9,281.6 920.6,281.6C919.2,281.6 918,282.1 917,283.2C916.1,284.2 915.7,285.5 915.7,287.2L915.7,298.5L910.4,298.5L910.4,283.2Z"/>
    <path android:fillColor="#ffffff" android:pathData="M1020,175C1020,199.8 999.8,220 975,220L645,220C620.2,220 600,199.8 600,175C600,150.2 620.2,130 645,130L975,130C999.8,130 1020,150.2 1020,175Z"/>
    <path android:fillColor="#212121" android:fillType="nonZero" android:pathData="M803.9,188.9C800.2,188.9 797.4,187.9 795.6,185.9C793.7,183.9 792.7,181 792.7,177.2L792.7,159.5L798.7,159.5L798.7,177.1C798.7,181.8 800.4,184.1 803.9,184.1C807.5,184.1 809.2,181.8 809.2,177.1L809.2,159.5L815.2,159.5L815.2,177.2C815.2,181 814.2,183.9 812.3,185.9C810.4,187.9 807.6,188.9 803.9,188.9Z"/>
    <path android:fillColor="#212121" android:fillType="nonZero" android:pathData="M821.4,159.5l5.9,0l0,29l-5.9,0z"/>
    <path android:pathData="M930,65C930,89.8 909.8,110 885,110L735,110C710.2,110 690,89.8 690,65C690,40.2 710.2,20 735,20L885,20C909.8,20 930,40.2 930,65Z">
        <aapt:attr name="android:fillColor">
            <gradient android:endX="690" android:endY="65"
                android:startX="930" android:startY="65" android:type="linear">
                <item android:color="#FFE44857" android:offset="0"/>
                <item android:color="#FFDA4968" android:offset="0.2"/>
                <item android:color="#FFBE4C96" android:offset="0.4"/>
                <item android:color="#FFA74EBC" android:offset="0.6"/>
                <item android:color="#FF9650D9" android:offset="0.7"/>
                <item android:color="#FF8252FB" android:offset="0.9"/>
                <item android:color="#FF7F52FF" android:offset="1"/>
            </gradient>
        </aapt:attr>
    </path>
    <path android:fillColor="#ffffff" android:fillType="nonZero" android:pathData="M830,85L790,85L790,45L830,45L809.6,64.7L830,85Z"/>
    <path android:fillColor="#1976D2" android:pathData="M370,402.5C370,427.3 349.8,447.5 325,447.5L175,447.5C150.2,447.5 130,427.3 130,402.5C130,377.7 150.2,357.5 175,357.5L325,357.5C349.8,357.5 370,377.7 370,402.5Z"/>
    <path android:fillColor="#ffffff" android:fillType="nonZero" android:pathData="M225,393.5C224,393.5 223.2,393.2 222.6,392.7C222,392.1 221.7,391.4 221.7,390.4C221.7,389.5 222,388.7 222.6,388.2C223.2,387.6 224,387.3 225,387.3C226,387.3 226.9,387.6 227.5,388.2C228.1,388.7 228.4,389.5 228.4,390.4C228.4,391.4 228.1,392.1 227.5,392.7C226.9,393.2 226.1,393.5 225,393.5ZM222.4,395.9L227.7,395.9L227.7,416.6L222.4,416.6L222.4,395.9Z"/>
    <path android:fillColor="#ffffff" android:fillType="nonZero" android:pathData="M245,417C242.3,417 240,416.4 238,415.2C236,414.1 234.5,412.3 233.5,410.1C232.5,407.9 232,405.2 232,402.1C232,399 232.5,396.4 233.5,394.1C234.5,391.9 236,390.2 238,389C240,387.8 242.3,387.2 245,387.2C247.7,387.2 250,387.8 251.9,389C253.9,390.2 255.4,391.9 256.4,394.1C257.4,396.4 257.9,399 257.9,402.1C257.9,405.2 257.4,407.9 256.4,410.1C255.4,412.3 253.9,414.1 251.9,415.2C250,416.4 247.7,417 245,417ZM245,412.3C247.2,412.3 248.9,411.4 250.1,409.6C251.4,407.8 252,405.3 252,402.1C252,399 251.4,396.5 250.1,394.7C248.9,392.9 247.2,391.9 245,391.9C242.8,391.9 241.1,392.9 239.8,394.7C238.5,396.5 237.9,399 237.9,402.1C237.9,405.3 238.5,407.8 239.8,409.6C241.1,411.4 242.8,412.3 245,412.3Z"/>
    <path android:fillColor="#ffffff" android:fillType="nonZero" android:pathData="M270.6,417C268.4,417 266.4,416.6 264.7,415.7C262.9,414.8 261.5,413.5 260.4,411.9L263.8,408.6C264.7,409.7 265.8,410.5 267.1,411.2C268.4,411.9 269.6,412.3 270.8,412.3C272,412.3 273.1,412 273.8,411.4C274.6,410.8 275,410.1 275,409.1C275,408.4 274.9,407.9 274.6,407.4C274.4,407 273.9,406.5 273.2,406.1C272.5,405.6 271.4,405 269.8,404.2C267.7,403.2 266.1,402.3 264.9,401.4C263.7,400.5 262.9,399.5 262.3,398.5C261.7,397.5 261.5,396.3 261.5,394.9C261.5,393.4 261.9,392 262.7,390.9C263.5,389.7 264.6,388.8 266.1,388.2C267.5,387.5 269.2,387.2 271.1,387.2C273.2,387.2 275,387.6 276.7,388.4C278.3,389.2 279.5,390.3 280.2,391.7L276.4,394.6C275.1,392.8 273.4,392 271.3,392C270.1,392 269.1,392.2 268.4,392.7C267.7,393.2 267.4,393.9 267.4,394.8C267.4,395.4 267.5,395.9 267.9,396.3C268.2,396.8 268.9,397.3 269.8,397.8C270.7,398.3 272.1,399 273.9,399.9C275.6,400.7 277,401.5 278,402.3C279,403.2 279.8,404.1 280.2,405.1C280.6,406.1 280.9,407.3 280.9,408.7C280.9,410.4 280.4,411.9 279.6,413.1C278.8,414.4 277.6,415.3 276,416C274.4,416.7 272.6,417 270.6,417Z"/>
    <path android:fillColor="#4CAF50" android:pathData="M370,232.5C370,257.3 349.8,277.5 325,277.5L175,277.5C150.2,277.5 130,257.3 130,232.5C130,207.7 150.2,187.5 175,187.5L325,187.5C349.8,187.5 370,207.7 370,232.5Z"/>
    <path android:fillColor="#ffffff" android:fillType="nonZero" android:pathData="M195.3,241.8L185.4,241.8L183.9,246.6L177.7,246.6L187.7,217.6L193,217.6L203,246.6L196.8,246.6L195.3,241.8ZM193.9,237L190.4,225.5L186.8,237L193.9,237Z"/>
    <path android:fillColor="#ffffff" android:fillType="nonZero" android:pathData="M205.5,231.4C205.5,228.9 205.5,227.1 205.4,225.9L210.3,225.9C210.5,227.1 210.6,228.3 210.6,229.5L210.7,229.5C211.2,228.3 212,227.3 213.3,226.6C214.6,225.9 216,225.5 217.5,225.5C219.9,225.5 221.7,226.3 222.9,227.9C224.1,229.5 224.7,231.9 224.7,235L224.7,246.6L219.4,246.6L219.4,234.9C219.4,233.1 219.2,231.8 218.6,231C218,230.2 217.1,229.8 215.8,229.8C214.3,229.8 213.2,230.3 212.2,231.3C211.3,232.4 210.8,233.7 210.8,235.3L210.8,246.6L205.5,246.6L205.5,231.4Z"/>
    <path android:fillColor="#ffffff" android:fillType="nonZero" android:pathData="M236.7,247C234,247 231.9,246 230.3,244.1C228.8,242.1 228,239.4 228,235.9C228,233.8 228.4,232 229.1,230.4C229.8,228.9 230.8,227.6 232.2,226.8C233.5,225.9 235.1,225.5 236.9,225.5C238.1,225.5 239.1,225.7 240.1,226.1C241,226.5 241.8,227.2 242.5,228L242.6,228L242.6,215.9L247.8,215.9L247.8,241.1C247.8,244 247.9,245.8 248,246.6L243,246.6C243,246.1 242.9,245.2 242.9,243.9L242.9,243.9C242.2,244.8 241.4,245.6 240.2,246.2C239.1,246.7 238,247 236.7,247ZM237.8,243C239.2,243 240.4,242.5 241.3,241.7C242.1,240.9 242.6,239.8 242.6,238.4L242.6,234.1C242.6,232.8 242.1,231.6 241.2,230.8C240.3,229.9 239.2,229.4 237.8,229.4C236.3,229.4 235.2,230 234.4,231.1C233.7,232.3 233.3,233.9 233.3,236C233.3,238.2 233.7,240 234.4,241.2C235.2,242.4 236.3,243 237.8,243Z"/>
    <path android:fillColor="#ffffff" android:fillType="nonZero" android:pathData="M252.2,231C252.2,228.6 252.2,226.9 252.1,225.9L257.1,225.9C257.2,227 257.3,228.2 257.3,229.6L257.3,230L257.4,230C257.9,228.6 258.9,227.5 260.2,226.7C261.5,225.9 263,225.5 264.7,225.5C265.1,225.5 265.5,225.5 266,225.6L266,229.8C265.9,229.8 265.5,229.7 265,229.7C263.7,229.7 262.4,230.1 261.3,230.8C260.1,231.5 259.2,232.5 258.5,233.7C257.9,234.9 257.5,236.2 257.5,237.5L257.5,246.6L252.2,246.6L252.2,231Z"/>
    <path android:fillColor="#ffffff" android:fillType="nonZero" android:pathData="M277.9,247C274.6,247 272,246.1 270.1,244.2C268.3,242.3 267.3,239.6 267.3,236.3C267.3,232.9 268.3,230.3 270.1,228.4C272,226.5 274.6,225.5 277.9,225.5C281.3,225.5 283.9,226.5 285.8,228.4C287.7,230.3 288.6,232.9 288.6,236.3C288.6,239.6 287.7,242.3 285.8,244.2C283.9,246.1 281.3,247 277.9,247ZM277.9,243.1C279.6,243.1 281,242.5 281.9,241.3C282.9,240.1 283.4,238.4 283.4,236.3C283.4,234.1 282.9,232.5 281.9,231.3C281,230 279.6,229.4 277.9,229.4C276.3,229.4 274.9,230 274,231.3C273,232.5 272.6,234.1 272.6,236.3C272.6,238.4 273,240.1 274,241.3C274.9,242.5 276.3,243.1 277.9,243.1Z"/>
    <path android:fillColor="#ffffff" android:fillType="nonZero" android:pathData="M295.6,223.5C294.5,223.5 293.7,223.2 293.1,222.7C292.5,222.1 292.2,221.4 292.2,220.4C292.2,219.5 292.5,218.7 293.1,218.2C293.7,217.6 294.5,217.3 295.6,217.3C296.6,217.3 297.4,217.6 298,218.2C298.7,218.7 299,219.5 299,220.4C299,221.4 298.7,222.1 298.1,222.7C297.4,223.2 296.6,223.5 295.6,223.5ZM293,225.9L298.2,225.9L298.2,246.6L293,246.6L293,225.9Z"/>
    <path android:fillColor="#ffffff" android:fillType="nonZero" android:pathData="M311.1,247C308.4,247 306.3,246 304.7,244.1C303.1,242.1 302.4,239.4 302.4,235.9C302.4,233.8 302.7,232 303.4,230.4C304.1,228.9 305.2,227.6 306.5,226.8C307.9,225.9 309.4,225.5 311.2,225.5C312.4,225.5 313.5,225.7 314.4,226.1C315.3,226.5 316.1,227.2 316.8,228L316.9,228L316.9,215.9L322.2,215.9L322.2,241.1C322.2,244 322.2,245.8 322.3,246.6L317.3,246.6C317.3,246.1 317.3,245.2 317.3,243.9L317.2,243.9C316.6,244.8 315.7,245.6 314.6,246.2C313.5,246.7 312.3,247 311.1,247ZM312.1,243C313.6,243 314.7,242.5 315.6,241.7C316.5,240.9 316.9,239.8 316.9,238.4L316.9,234.1C316.9,232.8 316.5,231.6 315.6,230.8C314.6,229.9 313.5,229.4 312.1,229.4C310.7,229.4 309.5,230 308.8,231.1C308,232.3 307.6,233.9 307.6,236C307.6,238.2 308,240 308.8,241.2C309.5,242.4 310.7,243 312.1,243Z"/>
</vector>
